{
  "usableSessionsCount": 11,
  "retiredSessionsCount": 0,
  "sessions": [
    {
      "id": "session_V5bKEUbXXh",
      "cookieJar": {
        "version": "tough-cookie@6.0.1",
        "storeType": "MemoryCookieStore",
        "rejectPublicSuffixes": true,
        "enableLooseMode": false,
        "allowSpecialUseDomain": true,
        "prefixSecurity": "silent",
        "cookies": []
      },
      "userData": {},
      "maxErrorScore": 3,
      "errorScoreDecrement": 0.5,
      "expiresAt": "2026-04-27T10:06:33.782Z",
      "createdAt": "2026-04-27T09:16:33.782Z",
      "usageCount": 0,
      "maxUsageCount": 50,
      "errorScore": 0
    },
    {
      "id": "session_Ooh21qaepr",
      "cookieJar": {
        "version": "tough-cookie@6.0.1",
        "storeType": "MemoryCookieStore",
        "rejectPublicSuffixes": true,
        "enableLooseMode": false,
        "allowSpecialUseDomain": true,
        "prefixSecurity": "silent",
        "cookies": [
          {
            "key": "__ddg1_",
            "value": "OVl1sVaWk45w7JSY7HyV",
            "expires": "2027-04-27T09:16:46.000Z",
            "domain": "pitergsm.ru",
            "path": "/",
            "httpOnly": true,
            "hostOnly": false,
            "creation": "2026-04-27T09:17:08.248Z",
            "lastAccessed": "2026-04-27T09:17:57.881Z"
          },
          {
            "key": "PHPSESSID",
            "value": "44ZWFMEc6w7ITXwsYddTpgiXhiaUMFC1",
            "expires": "2026-04-27T10:07:08.000Z",
            "domain": "pitergsm.ru",
            "path": "/",
            "httpOnly": true,
            "hostOnly": false,
            "creation": "2026-04-27T09:17:08.248Z",
            "lastAccessed": "2026-04-27T09:17:57.881Z"
          },
          {
            "key": "BITRIX_SM_CLEARED_CURRENT_CITY_ID",
            "value": "Y",
            "expires": "2027-04-22T09:16:46.000Z",
            "domain": "pitergsm.ru",
            "path": "/",
            "hostOnly": false,
            "creation": "2026-04-27T09:17:08.248Z",
            "lastAccessed": "2026-04-27T09:17:57.881Z"
          },
          {
            "key": "BITRIX_CONVERSION_CONTEXT_s1",
            "value": "%7B%22ID%22%3A14%2C%22EXPIRE%22%3A1777323540%2C%22UNIQUE%22%3A%5B%22conversion_visit_day%22%5D%7D",
            "expires": "2027-04-27T09:16:48.000Z",
            "domain": "pitergsm.ru",
            "path": "/",
            "hostOnly": false,
            "creation": "2026-04-27T09:17:08.248Z",
            "lastAccessed": "2026-04-27T09:17:57.881Z"
          },
          {
            "key": "theme",
            "value": "null",
            "expires": "2026-05-27T09:16:48.000Z",
            "domain": "pitergsm.ru",
            "path": "/",
            "hostOnly": true,
            "creation": "2026-04-27T09:17:08.248Z",
            "lastAccessed": "2026-04-27T09:17:57.881Z"
          },
          {
            "key": "mindboxDeviceUUID",
            "value": "cf9d64f3-19f6-41f2-b4a7-d26ab7980abc",
            "expires": "2027-06-01T09:16:48.000Z",
            "domain": "pitergsm.ru",
            "path": "/",
            "hostOnly": false,
            "creation": "2026-04-27T09:17:08.248Z",
            "lastAccessed": "2026-04-27T09:17:57.881Z"
          },
          {
            "key": "directCrm-session",
            "value": "%7B%22deviceGuid%22%3A%22cf9d64f3-19f6-41f2-b4a7-d26ab7980abc%22%7D",
            "expires": "2027-06-01T09:16:48.000Z",
            "domain": "pitergsm.ru",
            "path": "/",
            "hostOnly": false,
            "creation": "2026-04-27T09:17:08.248Z",
            "lastAccessed": "2026-04-27T09:17:57.881Z"
          },
          {
            "key": "tmr_lvid",
            "value": "3098797ac40eccf37f53b752d28bc569",
            "expires": "2027-03-26T09:17:52.000Z",
            "domain": "pitergsm.ru",
            "path": "/",
            "hostOnly": false,
            "creation": "2026-04-27T09:17:08.248Z",
            "lastAccessed": "2026-04-27T09:17:57.881Z"
          },
          {
            "key": "tmr_lvidTS",
            "value": "1777281408475",
            "expires": "2027-03-26T09:17:52.000Z",
            "domain": "pitergsm.ru",
            "path": "/",
            "hostOnly": false,
            "creation": "2026-04-27T09:17:08.248Z",
            "lastAccessed": "2026-04-27T09:17:57.881Z"
          },
          {
            "key": "_ym_uid",
            "value": "1777281409162466986",
            "expires": "2027-04-27T09:17:52.000Z",
            "domain": "pitergsm.ru",
            "path": "/",
            "secure": true,
            "hostOnly": false,
            "creation": "2026-04-27T09:17:08.248Z",
            "lastAccessed": "2026-04-27T09:17:57.881Z"
          },
          {
            "key": "_ym_d",
            "value": "1777281472",
            "expires": "2027-04-27T09:17:52.000Z",
            "domain": "pitergsm.ru",
            "path": "/",
            "secure": true,
            "hostOnly": false,
            "creation": "2026-04-27T09:17:08.248Z",
            "lastAccessed": "2026-04-27T09:17:57.881Z"
          },
          {
            "key": "_ymab_param",
            "value": "n5I81hZbRzr7_y7gZVQN2wNdH3uf-bz_mScj2ynYHwKC5q15Xq8h0r7V6p7F9IClT3JFdoo6Ewe9XU761TlBImw7pmo",
            "expires": "2027-04-27T09:17:52.000Z",
            "domain": "pitergsm.ru",
            "path": "/",
            "secure": true,
            "hostOnly": true,
            "creation": "2026-04-27T09:17:08.248Z",
            "lastAccessed": "2026-04-27T09:17:57.881Z"
          },
          {
            "key": "_userGUID",
            "value": "0:mogzgnm4:g_OpRBu562CJ3QB4fEu21gHpbqEG_hkG",
            "expires": "2027-06-01T09:17:52.000Z",
            "domain": "pitergsm.ru",
            "path": "/",
            "hostOnly": true,
            "creation": "2026-04-27T09:17:08.248Z",
            "lastAccessed": "2026-04-27T09:17:57.881Z"
          },
          {
            "key": "_ym_isad",
            "value": "2",
            "expires": "2026-04-28T05:16:48.000Z",
            "domain": "pitergsm.ru",
            "path": "/",
            "hostOnly": false,
            "creation": "2026-04-27T09:17:08.248Z",
            "lastAccessed": "2026-04-27T09:17:57.881Z"
          },
          {
            "key": "_ym_visorc",
            "value": "b",
            "expires": "2026-04-27T09:47:52.000Z",
            "domain": "pitergsm.ru",
            "path": "/",
            "hostOnly": false,
            "creation": "2026-04-27T09:17:08.249Z",
            "lastAccessed": "2026-04-27T09:17:57.881Z"
          },
          {
            "key": "__ddg8_",
            "value": "LIHFUiykJ1P5RrUE",
            "expires": "2026-04-27T09:37:53.000Z",
            "domain": "pitergsm.ru",
            "path": "/",
            "hostOnly": false,
            "creation": "2026-04-27T09:17:08.249Z",
            "lastAccessed": "2026-04-27T09:17:57.881Z"
          },
          {
            "key": "__ddg10_",
            "value": "1777281472",
            "expires": "2026-04-27T09:37:53.000Z",
            "domain": "pitergsm.ru",
            "path": "/",
            "hostOnly": false,
            "creation": "2026-04-27T09:17:08.249Z",
            "lastAccessed": "2026-04-27T09:17:57.881Z"
          },
          {
            "key": "__ddg9_",
            "value": "31.28.10.139",
            "expires": "2026-04-27T09:37:53.000Z",
            "domain": "pitergsm.ru",
            "path": "/",
            "hostOnly": false,
            "creation": "2026-04-27T09:17:08.249Z",
            "lastAccessed": "2026-04-27T09:17:57.881Z"
          },
          {
            "key": "domain_sid",
            "value": "1Fl1utHaIlDVG-aGunO9R%3A1777281409765",
            "expires": "2026-05-04T09:16:49.000Z",
            "domain": "pitergsm.ru",
            "path": "/",
            "hostOnly": true,
            "creation": "2026-04-27T09:17:08.249Z",
            "lastAccessed": "2026-04-27T09:17:57.881Z"
          },
          {
            "key": "tmr_detect",
            "value": "0%7C1777281474834",
            "expires": "2026-04-28T09:17:54.000Z",
            "domain": "pitergsm.ru",
            "path": "/",
            "hostOnly": true,
            "creation": "2026-04-27T09:17:08.249Z",
            "lastAccessed": "2026-04-27T09:17:57.882Z"
          },
          {
            "key": "Fuuid",
            "value": "f15dacb4-3480-427b-b819-9cda1a227e5a,1777281412",
            "expires": "2027-06-01T09:16:52.000Z",
            "domain": "pitergsm.ru",
            "path": "/",
            "secure": true,
            "hostOnly": true,
            "creation": "2026-04-27T09:17:08.249Z",
            "lastAccessed": "2026-04-27T09:17:57.881Z"
          },
          {
            "key": "dSesn",
            "value": "a083bec4-8a22-83c6-87dc-ac1ee3cecb9c",
            "expires": "2026-04-27T09:47:13.000Z",
            "domain": "pitergsm.ru",
            "path": "/",
            "hostOnly": false,
            "creation": "2026-04-27T09:17:33.282Z",
            "lastAccessed": "2026-04-27T09:17:57.881Z"
          },
          {
            "key": "_dvs",
            "value": "0:mogzh721:0fmcVXzx72T5fN_yuQmdUhiDQ5mhWhq9",
            "expires": "2026-04-27T09:47:52.000Z",
            "domain": "pitergsm.ru",
            "path": "/",
            "hostOnly": true,
            "creation": "2026-04-27T09:17:33.283Z",
            "lastAccessed": "2026-04-27T09:17:57.881Z"
          },
          {
            "key": "digi_uc",
            "value": "|v:177728:13680:31650:74832",
            "expires": "2027-04-27T09:17:52.000Z",
            "domain": "pitergsm.ru",
            "path": "/",
            "hostOnly": false,
            "creation": "2026-04-27T09:17:33.283Z",
            "lastAccessed": "2026-04-27T09:17:57.881Z"
          },
          {
            "key": "Dsign",
            "value": "y",
            "expires": "2026-04-27T09:17:55.000Z",
            "domain": "pitergsm.ru",
            "path": "/",
            "hostOnly": true,
            "creation": "2026-04-27T09:17:57.618Z",
            "lastAccessed": "2026-04-27T09:17:57.881Z"
          }
        ]
      },
      "userData": {},
      "maxErrorScore": 3,
      "errorScoreDecrement": 0.5,
      "expiresAt": "2026-04-27T10:06:33.786Z",
      "createdAt": "2026-04-27T09:16:33.786Z",
      "usageCount": 10,
      "maxUsageCount": 50,
      "errorScore": 0
    },
    {
      "id": "session_51bWJ8NHL5",
      "cookieJar": {
        "version": "tough-cookie@6.0.1",
        "storeType": "MemoryCookieStore",
        "rejectPublicSuffixes": true,
        "enableLooseMode": false,
        "allowSpecialUseDomain": true,
        "prefixSecurity": "silent",
        "cookies": []
      },
      "userData": {},
      "maxErrorScore": 3,
      "errorScoreDecrement": 0.5,
      "expiresAt": "2026-04-27T10:07:08.654Z",
      "createdAt": "2026-04-27T09:17:08.654Z",
      "usageCount": 0,
      "maxUsageCount": 50,
      "errorScore": 0
    },
    {
      "id": "session_1a93C4Su2K",
      "cookieJar": {
        "version": "tough-cookie@6.0.1",
        "storeType": "MemoryCookieStore",
        "rejectPublicSuffixes": true,
        "enableLooseMode": false,
        "allowSpecialUseDomain": true,
        "prefixSecurity": "silent",
        "cookies": []
      },
      "userData": {},
      "maxErrorScore": 3,
      "errorScoreDecrement": 0.5,
      "expiresAt": "2026-04-27T10:07:08.658Z",
      "createdAt": "2026-04-27T09:17:08.658Z",
      "usageCount": 0,
      "maxUsageCount": 50,
      "errorScore": 0
    },
    {
      "id": "session_z5OhNsMF7t",
      "cookieJar": {
        "version": "tough-cookie@6.0.1",
        "storeType": "MemoryCookieStore",
        "rejectPublicSuffixes": true,
        "enableLooseMode": false,
        "allowSpecialUseDomain": true,
        "prefixSecurity": "silent",
        "cookies": []
      },
      "userData": {},
      "maxErrorScore": 3,
      "errorScoreDecrement": 0.5,
      "expiresAt": "2026-04-27T10:07:08.662Z",
      "createdAt": "2026-04-27T09:17:08.662Z",
      "usageCount": 0,
      "maxUsageCount": 50,
      "errorScore": 0
    },
    {
      "id": "session_vJEVwosUMB",
      "cookieJar": {
        "version": "tough-cookie@6.0.1",
        "storeType": "MemoryCookieStore",
        "rejectPublicSuffixes": true,
        "enableLooseMode": false,
        "allowSpecialUseDomain": true,
        "prefixSecurity": "silent",
        "cookies": []
      },
      "userData": {},
      "maxErrorScore": 3,
      "errorScoreDecrement": 0.5,
      "expiresAt": "2026-04-27T10:07:13.987Z",
      "createdAt": "2026-04-27T09:17:13.987Z",
      "usageCount": 0,
      "maxUsageCount": 50,
      "errorScore": 0
    },
    {
      "id": "session_SU8Sf4zktH",
      "cookieJar": {
        "version": "tough-cookie@6.0.1",
        "storeType": "MemoryCookieStore",
        "rejectPublicSuffixes": true,
        "enableLooseMode": false,
        "allowSpecialUseDomain": true,
        "prefixSecurity": "silent",
        "cookies": []
      },
      "userData": {},
      "maxErrorScore": 3,
      "errorScoreDecrement": 0.5,
      "expiresAt": "2026-04-27T10:07:33.458Z",
      "createdAt": "2026-04-27T09:17:33.458Z",
      "usageCount": 0,
      "maxUsageCount": 50,
      "errorScore": 0
    },
    {
      "id": "session_HF7XSwJRpu",
      "cookieJar": {
        "version": "tough-cookie@6.0.1",
        "storeType": "MemoryCookieStore",
        "rejectPublicSuffixes": true,
        "enableLooseMode": false,
        "allowSpecialUseDomain": true,
        "prefixSecurity": "silent",
        "cookies": []
      },
      "userData": {},
      "maxErrorScore": 3,
      "errorScoreDecrement": 0.5,
      "expiresAt": "2026-04-27T10:07:33.463Z",
      "createdAt": "2026-04-27T09:17:33.463Z",
      "usageCount": 0,
      "maxUsageCount": 50,
      "errorScore": 0
    },
    {
      "id": "session_EnOfBiZcvK",
      "cookieJar": {
        "version": "tough-cookie@6.0.1",
        "storeType": "MemoryCookieStore",
        "rejectPublicSuffixes": true,
        "enableLooseMode": false,
        "allowSpecialUseDomain": true,
        "prefixSecurity": "silent",
        "cookies": []
      },
      "userData": {},
      "maxErrorScore": 3,
      "errorScoreDecrement": 0.5,
      "expiresAt": "2026-04-27T10:07:34.044Z",
      "createdAt": "2026-04-27T09:17:34.044Z",
      "usageCount": 0,
      "maxUsageCount": 50,
      "errorScore": 0
    },
    {
      "id": "session_L9w2l8XWUL",
      "cookieJar": {
        "version": "tough-cookie@6.0.1",
        "storeType": "MemoryCookieStore",
        "rejectPublicSuffixes": true,
        "enableLooseMode": false,
        "allowSpecialUseDomain": true,
        "prefixSecurity": "silent",
        "cookies": []
      },
      "userData": {},
      "maxErrorScore": 3,
      "errorScoreDecrement": 0.5,
      "expiresAt": "2026-04-27T10:07:34.051Z",
      "createdAt": "2026-04-27T09:17:34.051Z",
      "usageCount": 0,
      "maxUsageCount": 50,
      "errorScore": 0
    },
    {
      "id": "session_ldOm0fw05v",
      "cookieJar": {
        "version": "tough-cookie@6.0.1",
        "storeType": "MemoryCookieStore",
        "rejectPublicSuffixes": true,
        "enableLooseMode": false,
        "allowSpecialUseDomain": true,
        "prefixSecurity": "silent",
        "cookies": []
      },
      "userData": {},
      "maxErrorScore": 3,
      "errorScoreDecrement": 0.5,
      "expiresAt": "2026-04-27T10:07:34.228Z",
      "createdAt": "2026-04-27T09:17:34.228Z",
      "usageCount": 0,
      "maxUsageCount": 50,
      "errorScore": 0
    }
  ]
}